README.rst
setup.py
matterllo/__init__.py
matterllo/parser.py
matterllo/utils.py
matterllo.egg-info/PKG-INFO
matterllo.egg-info/SOURCES.txt
matterllo.egg-info/dependency_links.txt
matterllo.egg-info/requires.txt
matterllo.egg-info/top_level.txt
matterllo/hook/__init__.py
matterllo/hook/card.py
matterllo/hook/checklist.py
matterllo/hook/list.py