Metadata-Version: 1.1
Name: matterllo
Version: 0.1
Summary: Simple integration between Trello and Mattermost
Home-page: https://github.com/lujeni/matterllo
Author: Lujeni
Author-email: julien@thebault.co
License: BSD
Download-URL: https://github.com/lujeni/matterllo/tags
Platform: any
Classifier: License :: OSI Approved :: BSD License
Classifier: Operating System :: POSIX :: Linux
Classifier: Programming Language :: Python
Classifier: Programming Language :: Python :: 2.7
Classifier: Topic :: Software Development :: Libraries :: Python Modules
